scorable/__about__.py
scorable/__init__.py
scorable/client.py
scorable/datasets.py
scorable/execution_logs.py
scorable/judges.py
scorable/models.py
scorable/objectives.py
scorable/py.typed
scorable/skills.py
scorable/utils.py
scorable/generated/__init__.py
scorable/generated/openapi_aclient_README.md
scorable/generated/openapi_client_README.md
scorable/generated/openapi_aclient/__init__.py
scorable/generated/openapi_aclient/api_client.py
scorable/generated/openapi_aclient/api_response.py
scorable/generated/openapi_aclient/configuration.py
scorable/generated/openapi_aclient/exceptions.py
scorable/generated/openapi_aclient/rest.py
scorable/generated/openapi_aclient/api/__init__.py
scorable/generated/openapi_aclient/api/beta_api.py
scorable/generated/openapi_aclient/api/datasets_api.py
scorable/generated/openapi_aclient/api/evaluators_api.py
scorable/generated/openapi_aclient/api/execution_logs_api.py
scorable/generated/openapi_aclient/api/judges_api.py
scorable/generated/openapi_aclient/api/models_api.py
scorable/generated/openapi_aclient/api/objectives_api.py
scorable/generated/openapi_aclient/models/__init__.py
scorable/generated/openapi_aclient/models/batch_execution_status.py
scorable/generated/openapi_aclient/models/data_set_create.py
scorable/generated/openapi_aclient/models/data_set_create_request.py
scorable/generated/openapi_aclient/models/data_set_list.py
scorable/generated/openapi_aclient/models/data_set_type.py
scorable/generated/openapi_aclient/models/dataset_range_request.py
scorable/generated/openapi_aclient/models/evaluation_agent.py
scorable/generated/openapi_aclient/models/evaluation_agent_evaluation_approach_enum.py
scorable/generated/openapi_aclient/models/evaluation_agent_execute_request_request.py
scorable/generated/openapi_aclient/models/evaluation_agent_execute_response.py
scorable/generated/openapi_aclient/models/evaluation_agent_generate_example_request.py
scorable-1.6.7.dist-info/METADATA
scorable-1.6.7.dist-info/WHEEL
scorable-1.6.7.dist-info/licenses/LICENSE
scorable-1.6.7.dist-info/RECORD
