Metadata-Version: 2.4
Name: scorable
Version: 1.6.7
Summary: The Python SDK for API of Scorable
Project-URL: Homepage, https://scorable.ai/
Project-URL: Repository, https://github.com/root-signals/rs-sdk
Project-URL: CHANGELOG, https://sdk.scorable.ai/en/latest/CHANGELOG.html
Maintainer-email: Ari Heljakka <ari.heljakka@scorable.ai>
License: 
License-File: LICENSE
Classifier: Development Status :: 4 - Beta
Classifier: Intended Audience :: Developers
Classifier: License :: OSI Approved :: Apache Software License
Classifier: Operating System :: MacOS
Classifier: Operating System :: Microsoft :: Windows
Classifier: Operating System :: OS Independent
Classifier: Operating System :: POSIX
Classifier: Operating System :: POSIX :: Linux
Classifier: Programming Language :: Python :: 3.10
Classifier: Programming Language :: Python :: 3.11
Classifier: Programming Language :: Python :: 3.12
Classifier: Programming Language :: Python :: 3.13
Classifier: Topic :: Scientific/Engineering :: Artificial Intelligence
Classifier: Topic :: Software Development :: Libraries :: Python Modules
Classifier: Typing :: Typed
Requires-Python: >=3.10
Requires-Dist: aiohttp
Requires-Dist: aiohttp-retry
Requires-Dist: aioitertools
Requires-Dist: asgiref
Requires-Dist: pydantic<3,>=2.6.2
Requires-Dist: python-dateutil
Requires-Dist: requests
Requires-Dist: typing-extensions
Requires-Dist: validators
Provides-Extra: dev
Requires-Dist: furo; extra == 'dev'
Requires-Dist: hatch; extra == 'dev'
Requires-Dist: mypy==1.14.1; extra == 'dev'
Requires-Dist: myst-parser; extra == 'dev'
Requires-Dist: pre-commit; extra == 'dev'
Requires-Dist: pytest; extra == 'dev'
Requires-Dist: pytest-asyncio; extra == 'dev'
Requires-Dist: ruff; extra == 'dev'
Requires-Dist: sphinx; extra == 'dev'
Requires-Dist: sphinx-autoapi; extra == 'dev'
Requires-Dist: sphinx-markdown-builder; extra == 'dev'
Requires-Dist: twine; extra == 'dev'
Requires-Dist: types-requests; extra == 'dev'
Requires-Dist: validators; extra == 'dev'
